gptfunctionutil/__init__.py
gptfunctionutil/converter_core.py
gptfunctionutil/convertutil.py
gptfunctionutil/errors.py
gptfunctionutil/functionlib.py
gptfunctionutil/functionlib_discord.py
gptfunctionutil/logger.py
gptfunctionutil/single_call.py
gptfunctionutil/types.py
gptfunctionutil/util.py
gptfunctionutil-0.3.8.0.dist-info/licenses/LICENSE
gptfunctionutil-0.3.8.0.dist-info/METADATA
gptfunctionutil-0.3.8.0.dist-info/WHEEL
gptfunctionutil-0.3.8.0.dist-info/top_level.txt
gptfunctionutil-0.3.8.0.dist-info/RECORD
