Metadata-Version: 2.4
Name: gptfunctionutil
Version: 0.3.8.0
Summary: A simple package for the purpose of providing a set of utilities that make it easier to invoke python functions and coroutines using OpenAI's GPT models.
Author-email: Crosswave Omega <xtream2pro@gmail.com>
License: MIT License
Project-URL: Homepage, https://github.com/CrosswaveOmega/GPT-Function-Calling-Utility
Keywords: OpenAI,Function Calling API,GPT,asyncio
Requires-Python: >=3.10
License-File: LICENSE
Requires-Dist: openai>=1.93.0
Requires-Dist: ollama>=0.5.1
Requires-Dist: sympy>=1.14.0
Requires-Dist: pydantic>=2.0.0
Provides-Extra: discord
Requires-Dist: discord>=2.3.2; extra == "discord"
Provides-Extra: spark
Requires-Dist: pyspark>=4.0.0; extra == "spark"
Provides-Extra: test
Requires-Dist: bandit[toml]==1.8.5; extra == "test"
Requires-Dist: black==25.1.0; extra == "test"
Requires-Dist: check-manifest==0.50; extra == "test"
Requires-Dist: flake8-bugbear==24.12.12; extra == "test"
Requires-Dist: flake8-docstrings; extra == "test"
Requires-Dist: flake8-formatter_junit_xml; extra == "test"
Requires-Dist: flake8; extra == "test"
Requires-Dist: flake8-pyproject; extra == "test"
Requires-Dist: pre-commit==4.2.0; extra == "test"
Requires-Dist: pylint==3.3.7; extra == "test"
Requires-Dist: pylint_junit; extra == "test"
Requires-Dist: pytest-cov==6.2.1; extra == "test"
Requires-Dist: pytest-mock<3.10.1; extra == "test"
Requires-Dist: pytest-runner; extra == "test"
Requires-Dist: pytest==8.4.1; extra == "test"
Requires-Dist: pytest-github-actions-annotate-failures; extra == "test"
Requires-Dist: shellcheck-py==0.10.0.1; extra == "test"
Dynamic: license-file
